{
  "version": 2,
  "date": "2020-12-15T23:57:09.053Z",
  "database": [
    {
      "id": "3fa5fde1-fefe-4245-a23c-13ed5b17b4c8",
      "name": "Lister",
      "description": "",
      "isDefault": false,
      "headers": [
        {
          "id": "d4a0c7ad-fb37-444c-a320-44fd2cdf9eae",
          "idCategory": "3fa5fde1-fefe-4245-a23c-13ed5b17b4c8",
          "name": "Todo",
          "items": [
            {
              "id": "374128fd-d289-4b61-9023-adb9298fc647",
              "idHeader": "d4a0c7ad-fb37-444c-a320-44fd2cdf9eae",
              "text": "Changer un item de liste",
              "checked": false,
              "subs": []
            },
            {
              "id": "47d4f1e6-cd09-4172-aff4-b38d33db6070",
              "idHeader": "d4a0c7ad-fb37-444c-a320-44fd2cdf9eae",
              "text": "Fix subscription",
              "checked": true,
              "subs": []
            },
            {
              "id": "68813a25-2fce-470a-96b5-2c146ad3ec42",
              "idHeader": "d4a0c7ad-fb37-444c-a320-44fd2cdf9eae",
              "text": "Quick add checked",
              "checked": false,
              "subs": []
            },
            {
              "id": "767a2cdf-3bbf-49bb-abe1-5dcdaf061aba",
              "idHeader": "d4a0c7ad-fb37-444c-a320-44fd2cdf9eae",
              "text": "Détruire une catégorie",
              "checked": true,
              "subs": []
            },
            {
              "id": "c5c153c7-26dc-4ce9-9595-5b092a3401d5",
              "idHeader": "d4a0c7ad-fb37-444c-a320-44fd2cdf9eae",
              "text": "Quick list",
              "checked": true,
              "subs": []
            },
            {
              "id": "dbdd07ef-fefc-4209-a4a3-86c3e2fc79f2",
              "idHeader": "d4a0c7ad-fb37-444c-a320-44fd2cdf9eae",
              "text": "Scroller les items",
              "checked": true,
              "subs": []
            }
          ]
        }
      ]
    },
    {
      "id": "6ed44084-62b5-4208-b27f-d26203f72fb9",
      "name": "Magasins",
      "description": "",
      "isDefault": false,
      "headers": [
        {
          "id": "66663558-2c9b-4463-a822-526375d95512",
          "name": "Nettoyage",
          "items": [],
          "idCategory": "6ed44084-62b5-4208-b27f-d26203f72fb9"
        },
        {
          "id": "8bcb993e-9d23-4351-8875-d6198ead6fc8",
          "idCategory": "6ed44084-62b5-4208-b27f-d26203f72fb9",
          "name": "Walmarde",
          "items": [
            {
              "id": "11dce100-ce7b-4f7f-8904-22ee647fe029",
              "idHeader": "8bcb993e-9d23-4351-8875-d6198ead6fc8",
              "text": "Old roy",
              "checked": false,
              "subs": []
            },
            {
              "id": "ac49f4a2-1a46-42d6-8db0-57d4a804e79f",
              "idHeader": "8bcb993e-9d23-4351-8875-d6198ead6fc8",
              "text": "Gros tape à boîte",
              "checked": false,
              "subs": []
            },
            {
              "id": "e962c5d2-fb46-4f6a-858d-08c72e71b6d3",
              "idHeader": "8bcb993e-9d23-4351-8875-d6198ead6fc8",
              "text": "Shower spray",
              "checked": false,
              "subs": []
            }
          ]
        },
        {
          "id": "bb0042b4-e06d-439e-bd01-0ce882bbbded",
          "idCategory": "6ed44084-62b5-4208-b27f-d26203f72fb9",
          "name": "Canadian-Tire",
          "items": [
            {
              "id": "84f2b761-56f4-4223-a2e0-0afbc672634e",
              "idHeader": "bb0042b4-e06d-439e-bd01-0ce882bbbded",
              "text": "Invisible glass",
              "checked": true,
              "subs": []
            },
            {
              "id": "c87fdfea-6749-4f3b-acce-b56cface3a0e",
              "idHeader": "bb0042b4-e06d-439e-bd01-0ce882bbbded",
              "text": "Stainless cleaner",
              "checked": false,
              "subs": []
            }
          ]
        }
      ]
    },
    {
      "id": "ffa8eb95-eb5d-488f-bace-208c490fa609",
      "name": "Foodz",
      "description": "",
      "isDefault": true,
      "headers": [
        {
          "id": "322dfa62-f43c-4335-a78a-c8d17da3c654",
          "idCategory": "ffa8eb95-eb5d-488f-bace-208c490fa609",
          "name": "Laitier",
          "items": [
            {
              "id": "54d3a37b-268f-4657-ab76-7b6ba901eca2",
              "idHeader": "322dfa62-f43c-4335-a78a-c8d17da3c654",
              "text": "Lait",
              "checked": false,
              "subs": [
                {
                  "id": "78fc3f4b-d6fa-495b-8fcb-19c8b92fabf2",
                  "idItem": "54d3a37b-268f-4657-ab76-7b6ba901eca2",
                  "text": "2%",
                  "rank": 1,
                  "checked": false
                },
                {
                  "id": "85659fb3-4077-4154-8d49-84116cf45bf5",
                  "idItem": "54d3a37b-268f-4657-ab76-7b6ba901eca2",
                  "text": "3.25%",
                  "rank": 2,
                  "checked": false
                }
              ]
            },
            {
              "id": "736b8c3f-049e-447e-afbb-71f3728918c0",
              "idHeader": "322dfa62-f43c-4335-a78a-c8d17da3c654",
              "text": "Crème",
              "checked": false,
              "subs": [
                {
                  "id": "178f8d85-2d97-42d5-8b0f-1976657a9411",
                  "idItem": "736b8c3f-049e-447e-afbb-71f3728918c0",
                  "text": " café",
                  "rank": 1,
                  "checked": false
                },
                {
                  "id": "de83e32f-e32f-4d25-a877-fb5a5ff4a0f0",
                  "idItem": "736b8c3f-049e-447e-afbb-71f3728918c0",
                  "text": " épaisse",
                  "rank": 2,
                  "checked": false
                }
              ]
            },
            {
              "id": "9fd9e30c-b6d8-44f5-98fe-2a77e4225a4f",
              "idHeader": "322dfa62-f43c-4335-a78a-c8d17da3c654",
              "text": "Fromage",
              "checked": true,
              "subs": [
                {
                  "id": "63a074d9-9318-457d-bd00-4db8736ad1d9",
                  "idItem": "9fd9e30c-b6d8-44f5-98fe-2a77e4225a4f",
                  "text": "Mozzarella",
                  "rank": 2,
                  "checked": false
                },
                {
                  "id": "b0ac6fe6-02bc-47ad-a1a8-372c6047d45b",
                  "idItem": "9fd9e30c-b6d8-44f5-98fe-2a77e4225a4f",
                  "text": "Cheddar",
                  "rank": 1,
                  "checked": false
                }
              ]
            }
          ]
        },
        {
          "id": "7484a5a8-b3ef-48b3-9fa8-2b6b216cfb3e",
          "name": "Légumes",
          "items": [
            {
              "id": "34c4d791-6bf1-43aa-a718-b4609b03b1a4",
              "idHeader": "7484a5a8-b3ef-48b3-9fa8-2b6b216cfb3e",
              "text": "Laitue",
              "checked": false,
              "subs": []
            },
            {
              "id": "63cb293d-50bf-40a8-b2db-ca5403cc9c9c",
              "idHeader": "7484a5a8-b3ef-48b3-9fa8-2b6b216cfb3e",
              "text": "Champignons",
              "checked": false,
              "subs": [
                {
                  "id": "d5bc7628-9056-4912-99ee-0f72a3b38fd7",
                  "idItem": "63cb293d-50bf-40a8-b2db-ca5403cc9c9c",
                  "text": "pleurottes",
                  "rank": 1,
                  "checked": false
                }
              ]
            },
            {
              "id": "7a05351f-2d75-4a91-b590-bfe056e1dccc",
              "idHeader": "7484a5a8-b3ef-48b3-9fa8-2b6b216cfb3e",
              "text": "Patates",
              "checked": false,
              "subs": [
                {
                  "id": "6ac836a0-ca86-4833-9782-79acecadf0af",
                  "idItem": "7a05351f-2d75-4a91-b590-bfe056e1dccc",
                  "text": " grelots",
                  "rank": 1,
                  "checked": false
                },
                {
                  "id": "a7651a6e-5bfc-4cc0-9cf0-ac2e506f759b",
                  "idItem": "7a05351f-2d75-4a91-b590-bfe056e1dccc",
                  "text": " au four",
                  "rank": 2,
                  "checked": false
                }
              ]
            },
            {
              "id": "7db22a1a-2af5-410b-b36a-81c63fb74840",
              "idHeader": "7484a5a8-b3ef-48b3-9fa8-2b6b216cfb3e",
              "text": "Poivrons",
              "checked": false,
              "subs": [
                {
                  "id": "0310c925-f708-4293-a3bb-8f041ee638d4",
                  "idItem": "7db22a1a-2af5-410b-b36a-81c63fb74840",
                  "text": "vert",
                  "rank": 2,
                  "checked": false
                },
                {
                  "id": "f9560600-f30e-4857-aaa3-abb649101862",
                  "idItem": "7db22a1a-2af5-410b-b36a-81c63fb74840",
                  "text": "rouge",
                  "rank": 1,
                  "checked": false
                }
              ]
            },
            {
              "id": "a65dbc88-91ef-4070-bd6f-15b5514f83a0",
              "idHeader": "7484a5a8-b3ef-48b3-9fa8-2b6b216cfb3e",
              "text": "Bananes",
              "checked": false,
              "subs": []
            },
            {
              "id": "b76edeff-2b19-42d7-87b2-3e86cec7fef3",
              "idHeader": "7484a5a8-b3ef-48b3-9fa8-2b6b216cfb3e",
              "text": "Salade",
              "checked": false,
              "subs": [
                {
                  "id": "d35e79fd-85af-4971-850f-ff75224f3476",
                  "idItem": "b76edeff-2b19-42d7-87b2-3e86cec7fef3",
                  "text": " kit",
                  "rank": 1,
                  "checked": false
                }
              ]
            },
            {
              "id": "c4c84182-670c-4bd0-9b8a-a19182521206",
              "idHeader": "7484a5a8-b3ef-48b3-9fa8-2b6b216cfb3e",
              "text": "Oignons",
              "checked": false,
              "subs": [
                {
                  "id": "6e8d8eb2-f8dd-4fe1-bd5e-30574419d862",
                  "idItem": "c4c84182-670c-4bd0-9b8a-a19182521206",
                  "text": " rouge",
                  "rank": 1,
                  "checked": false
                }
              ]
            },
            {
              "id": "ffa32eed-f1c1-4062-a4f3-cc0088d33d9a",
              "idHeader": "7484a5a8-b3ef-48b3-9fa8-2b6b216cfb3e",
              "text": "Tomates",
              "checked": false,
              "subs": []
            }
          ],
          "idCategory": "ffa8eb95-eb5d-488f-bace-208c490fa609"
        },
        {
          "id": "c45a8b37-fab0-443f-8b09-02d005abb0b8",
          "name": "Viande",
          "items": [
            {
              "id": "2045fb71-c847-45a4-8a6e-870172203e16",
              "idHeader": "c45a8b37-fab0-443f-8b09-02d005abb0b8",
              "text": "Smoked meat",
              "checked": true,
              "subs": []
            },
            {
              "id": "2bf86f03-bc81-498a-8e1d-4c729bcb937d",
              "idHeader": "c45a8b37-fab0-443f-8b09-02d005abb0b8",
              "text": "Viande froide",
              "checked": false,
              "subs": []
            },
            {
              "id": "2e619853-a3b7-4aae-bd5e-edaa4f472c63",
              "idHeader": "c45a8b37-fab0-443f-8b09-02d005abb0b8",
              "text": "Bacon 🥓",
              "checked": false,
              "subs": []
            },
            {
              "id": "4d450fee-fce9-47b6-bde7-e75af5696114",
              "idHeader": "c45a8b37-fab0-443f-8b09-02d005abb0b8",
              "text": "Veau vache cochon",
              "checked": false,
              "subs": []
            },
            {
              "id": "6f5db630-e126-4587-8520-ad173a396290",
              "idHeader": "c45a8b37-fab0-443f-8b09-02d005abb0b8",
              "text": "Poulet",
              "checked": false,
              "subs": [
                {
                  "id": "38f67778-5dc7-4158-8852-b456ef6213af",
                  "idItem": "6f5db630-e126-4587-8520-ad173a396290",
                  "text": "ailes",
                  "rank": 1,
                  "checked": false
                },
                {
                  "id": "6e1c113a-cf0f-4cfc-8b8f-be8ffbe6151f",
                  "idItem": "6f5db630-e126-4587-8520-ad173a396290",
                  "text": "hdc",
                  "rank": 2,
                  "checked": false
                }
              ]
            },
            {
              "id": "81840c9d-05f4-4a3e-a7a2-d94c9c853604",
              "idHeader": "c45a8b37-fab0-443f-8b09-02d005abb0b8",
              "text": "Saucisses",
              "checked": false,
              "subs": [
                {
                  "id": "57286fe2-2b4e-4da9-a259-91d07d19c2f3",
                  "idItem": "81840c9d-05f4-4a3e-a7a2-d94c9c853604",
                  "text": " déjeuner",
                  "rank": 2,
                  "checked": false
                },
                {
                  "id": "d50d2bee-0b2d-4c21-a692-93f5e58488ab",
                  "idItem": "81840c9d-05f4-4a3e-a7a2-d94c9c853604",
                  "text": " italienne",
                  "rank": 1,
                  "checked": false
                }
              ]
            },
            {
              "id": "95102d89-e62a-4b56-9c03-409b68c191f6",
              "idHeader": "c45a8b37-fab0-443f-8b09-02d005abb0b8",
              "text": "Steak",
              "checked": false,
              "subs": []
            },
            {
              "id": "aa246123-f903-4dd1-b0bd-f6d9744c35b9",
              "idHeader": "c45a8b37-fab0-443f-8b09-02d005abb0b8",
              "text": "Bœuf",
              "checked": false,
              "subs": [
                {
                  "id": "501b1bf5-5cff-454f-a269-b2f268be68ef",
                  "idItem": "aa246123-f903-4dd1-b0bd-f6d9744c35b9",
                  "text": "Cube",
                  "rank": 1,
                  "checked": false
                },
                {
                  "id": "f1794445-3a99-4c8a-82ca-0cabda8faaca",
                  "idItem": "aa246123-f903-4dd1-b0bd-f6d9744c35b9",
                  "text": "Palette",
                  "rank": 2,
                  "checked": false
                }
              ]
            },
            {
              "id": "e356d9bd-128c-4cda-aec2-615b80086981",
              "idHeader": "c45a8b37-fab0-443f-8b09-02d005abb0b8",
              "text": "Pepperoni",
              "checked": true,
              "subs": [
                {
                  "id": "6653286f-22fe-433b-856a-0e5ffdd7d5c9",
                  "idItem": "e356d9bd-128c-4cda-aec2-615b80086981",
                  "text": "sec",
                  "rank": 2,
                  "checked": false
                },
                {
                  "id": "f93c10ed-7745-4e8e-8cb6-58d135c94be6",
                  "idItem": "e356d9bd-128c-4cda-aec2-615b80086981",
                  "text": " Roma",
                  "rank": 1,
                  "checked": false
                }
              ]
            }
          ],
          "idCategory": "ffa8eb95-eb5d-488f-bace-208c490fa609"
        },
        {
          "id": "d41b2a41-9d29-4a6e-9b9a-644b52238ff3",
          "name": "Boulangerie",
          "items": [
            {
              "id": "50adfb56-96ff-46e5-beee-d2ee17736459",
              "idHeader": "d41b2a41-9d29-4a6e-9b9a-644b52238ff3",
              "text": "Crumpets",
              "checked": false,
              "subs": []
            },
            {
              "id": "88b343fd-8399-41a6-8ffc-9527d3ed7635",
              "idHeader": "d41b2a41-9d29-4a6e-9b9a-644b52238ff3",
              "text": "Pain",
              "checked": false,
              "subs": [
                {
                  "id": "19ef479c-0f8f-4f5d-bdcb-038a71f57b9e",
                  "idItem": "88b343fd-8399-41a6-8ffc-9527d3ed7635",
                  "text": "ciabata",
                  "rank": 1,
                  "checked": false
                },
                {
                  "id": "5e0f50fa-69f7-4158-b927-b7fb4be888b7",
                  "idItem": "88b343fd-8399-41a6-8ffc-9527d3ed7635",
                  "text": " tranché",
                  "rank": 2,
                  "checked": false
                }
              ]
            },
            {
              "id": "9828f62c-2d09-4014-b304-028b90120767",
              "idHeader": "d41b2a41-9d29-4a6e-9b9a-644b52238ff3",
              "text": "Submarine",
              "checked": true,
              "subs": []
            },
            {
              "id": "a45eaa6a-3990-4ede-87e6-e5834b218fb9",
              "idHeader": "d41b2a41-9d29-4a6e-9b9a-644b52238ff3",
              "text": "Cookies",
              "checked": false,
              "subs": []
            },
            {
              "id": "c32db6da-5268-4819-a6be-fb1c22378ac6",
              "idHeader": "d41b2a41-9d29-4a6e-9b9a-644b52238ff3",
              "text": "Muffin",
              "checked": false,
              "subs": []
            }
          ],
          "idCategory": "ffa8eb95-eb5d-488f-bace-208c490fa609"
        },
        {
          "id": "f7c599bf-bbb4-42ce-919b-663eb547683f",
          "name": "Épicerie",
          "items": [
            {
              "id": "01dd7b2f-5e1b-4611-99b8-d6655f6efccc",
              "idHeader": "f7c599bf-bbb4-42ce-919b-663eb547683f",
              "text": "Sushi ",
              "checked": false,
              "subs": []
            },
            {
              "id": "061a88fe-2ce0-421e-aa14-268adee0a7e4",
              "idHeader": "f7c599bf-bbb4-42ce-919b-663eb547683f",
              "text": "Bouillons",
              "checked": false,
              "subs": [
                {
                  "id": "1e5ca150-d74a-48a9-9963-190d77f138d6",
                  "idItem": "061a88fe-2ce0-421e-aa14-268adee0a7e4",
                  "text": " boeuf",
                  "rank": 1,
                  "checked": false
                },
                {
                  "id": "83562d6b-41fd-4139-b1ee-a0a2d5125783",
                  "idItem": "061a88fe-2ce0-421e-aa14-268adee0a7e4",
                  "text": " ",
                  "rank": 2,
                  "checked": false
                }
              ]
            },
            {
              "id": "0691c17d-a47d-4e5d-bcd7-1e178d402e16",
              "idHeader": "f7c599bf-bbb4-42ce-919b-663eb547683f",
              "text": "Huile",
              "checked": false,
              "subs": [
                {
                  "id": "3fd8d6d5-34a4-4e14-9e1c-4cd4d5e7840a",
                  "idItem": "0691c17d-a47d-4e5d-bcd7-1e178d402e16",
                  "text": "olive",
                  "rank": 1,
                  "checked": false
                },
                {
                  "id": "403e9c48-d42b-4361-89bc-35ee68f7f7a8",
                  "idItem": "0691c17d-a47d-4e5d-bcd7-1e178d402e16",
                  "text": "tournesol",
                  "rank": 2,
                  "checked": false
                }
              ]
            },
            {
              "id": "28f2a186-c2d6-41de-841e-c334e7336946",
              "idHeader": "f7c599bf-bbb4-42ce-919b-663eb547683f",
              "text": "Thé",
              "checked": false,
              "subs": [
                {
                  "id": "11274c0a-41a8-4501-be0d-dd056e20ced5",
                  "idItem": "28f2a186-c2d6-41de-841e-c334e7336946",
                  "text": " glacé",
                  "rank": 1,
                  "checked": false
                },
                {
                  "id": "49f5ad84-081f-4267-ab84-9bf9484e0694",
                  "idItem": "28f2a186-c2d6-41de-841e-c334e7336946",
                  "text": " marocain",
                  "rank": 2,
                  "checked": false
                }
              ]
            },
            {
              "id": "34166fc3-8600-4072-bcb6-10aee0e17e7e",
              "idHeader": "f7c599bf-bbb4-42ce-919b-663eb547683f",
              "text": "Can",
              "checked": false,
              "subs": [
                {
                  "id": "efc26ddb-dea0-4db6-a5a0-7bd5630282d5",
                  "idItem": "34166fc3-8600-4072-bcb6-10aee0e17e7e",
                  "text": "toto",
                  "rank": 1,
                  "checked": false
                }
              ]
            },
            {
              "id": "3cebc3db-80fc-4365-84cf-dfe1d7e39da6",
              "idHeader": "f7c599bf-bbb4-42ce-919b-663eb547683f",
              "text": "Papier",
              "checked": false,
              "subs": [
                {
                  "id": "436ca5e0-6a67-4501-9d0c-f0606fc8e3d8",
                  "idItem": "3cebc3db-80fc-4365-84cf-dfe1d7e39da6",
                  "text": " parchemin",
                  "rank": 2,
                  "checked": false
                },
                {
                  "id": "ef0461ae-fe03-4f01-b295-7bb8dadb0739",
                  "idItem": "3cebc3db-80fc-4365-84cf-dfe1d7e39da6",
                  "text": "Alu",
                  "rank": 1,
                  "checked": false
                }
              ]
            },
            {
              "id": "5f7f33a8-f196-4ce9-bb2a-e314dbf6806e",
              "idHeader": "f7c599bf-bbb4-42ce-919b-663eb547683f",
              "text": "Pâtes",
              "checked": false,
              "subs": [
                {
                  "id": "800576fd-2c0f-4425-bdee-27c94c734e93",
                  "idItem": "5f7f33a8-f196-4ce9-bb2a-e314dbf6806e",
                  "text": " spaghetti",
                  "rank": 2,
                  "checked": false
                },
                {
                  "id": "d03d0bcf-0a15-4ff9-97c0-13de39f4dc9c",
                  "idItem": "5f7f33a8-f196-4ce9-bb2a-e314dbf6806e",
                  "text": " lasagne",
                  "rank": 1,
                  "checked": false
                }
              ]
            },
            {
              "id": "605915fe-99a1-48c6-bfef-0816fddd8203",
              "idHeader": "f7c599bf-bbb4-42ce-919b-663eb547683f",
              "text": "Congelé",
              "checked": false,
              "subs": [
                {
                  "id": "7ba00c6e-9895-4c06-a5b0-07fa6be82756",
                  "idItem": "605915fe-99a1-48c6-bfef-0816fddd8203",
                  "text": "pizza",
                  "rank": 1,
                  "checked": false
                },
                {
                  "id": "fc527d0c-0ceb-41a7-9678-65758f17b457",
                  "idItem": "605915fe-99a1-48c6-bfef-0816fddd8203",
                  "text": "plats",
                  "rank": 2,
                  "checked": false
                }
              ]
            },
            {
              "id": "63d61aef-f5bc-40bc-b196-7ff9f7403977",
              "idHeader": "f7c599bf-bbb4-42ce-919b-663eb547683f",
              "text": "Sauce BBQ",
              "checked": false,
              "subs": []
            },
            {
              "id": "6ba71c36-8960-409f-99fb-1b00496a439e",
              "idHeader": "f7c599bf-bbb4-42ce-919b-663eb547683f",
              "text": "Sauce tomate",
              "checked": false,
              "subs": []
            },
            {
              "id": "84636f11-794e-4600-a75c-71478b010b27",
              "idHeader": "f7c599bf-bbb4-42ce-919b-663eb547683f",
              "text": "Café",
              "checked": false,
              "subs": [
                {
                  "id": "0c912fc9-d59f-4c94-91ef-8e5e5d110270",
                  "idItem": "84636f11-794e-4600-a75c-71478b010b27",
                  "text": "Lavazza",
                  "rank": 2,
                  "checked": false
                },
                {
                  "id": "c19ca4ac-b051-49d3-a854-26e333a2857f",
                  "idItem": "84636f11-794e-4600-a75c-71478b010b27",
                  "text": "Van Houtte",
                  "rank": 1,
                  "checked": false
                }
              ]
            },
            {
              "id": "8b56bcc6-c4b6-4bb8-9940-8de3b06c69e4",
              "idHeader": "f7c599bf-bbb4-42ce-919b-663eb547683f",
              "text": "Tomates",
              "checked": false,
              "subs": []
            },
            {
              "id": "c99fdb4c-65f6-4d8b-85e2-93f640b1cd00",
              "idHeader": "f7c599bf-bbb4-42ce-919b-663eb547683f",
              "text": "Jus",
              "checked": false,
              "subs": [
                {
                  "id": "7b466807-92f6-4273-b68b-0bccface5e50",
                  "idItem": "c99fdb4c-65f6-4d8b-85e2-93f640b1cd00",
                  "text": "oxia",
                  "rank": 2,
                  "checked": false
                },
                {
                  "id": "adbb7245-40bd-4b71-a6ce-ab921b3f1678",
                  "idItem": "c99fdb4c-65f6-4d8b-85e2-93f640b1cd00",
                  "text": "orange",
                  "rank": 1,
                  "checked": false
                }
              ]
            },
            {
              "id": "cfdf5b45-4aa1-40b3-bb94-ff0ca05fd1b8",
              "idHeader": "f7c599bf-bbb4-42ce-919b-663eb547683f",
              "text": "Moutarde",
              "checked": false,
              "subs": [
                {
                  "id": "8c79764a-4ca2-4063-8215-5feb023c6a27",
                  "idItem": "cfdf5b45-4aa1-40b3-bb94-ff0ca05fd1b8",
                  "text": "Forte",
                  "rank": 1,
                  "checked": false
                },
                {
                  "id": "fdf09385-a5f7-4210-87cb-48af69cff6de",
                  "idItem": "cfdf5b45-4aa1-40b3-bb94-ff0ca05fd1b8",
                  "text": "Sèche",
                  "rank": 2,
                  "checked": false
                }
              ]
            },
            {
              "id": "e41440b3-fc9a-4fb6-a77a-b13a1e085e9a",
              "idHeader": "f7c599bf-bbb4-42ce-919b-663eb547683f",
              "text": "Orge",
              "checked": false,
              "subs": []
            },
            {
              "id": "e4a57e7d-1680-4579-8f0f-423ab150d8c0",
              "idHeader": "f7c599bf-bbb4-42ce-919b-663eb547683f",
              "text": "Dog food",
              "checked": false,
              "subs": [
                {
                  "id": "9dd52550-9ea1-484d-8a55-c0ee3eaf3508",
                  "idItem": "e4a57e7d-1680-4579-8f0f-423ab150d8c0",
                  "text": "Mou",
                  "rank": 1,
                  "checked": false
                },
                {
                  "id": "b08a18ba-beb3-44cb-aeb9-e2b1021f34a2",
                  "idItem": "e4a57e7d-1680-4579-8f0f-423ab150d8c0",
                  "text": "Gâterie",
                  "rank": 2,
                  "checked": false
                }
              ]
            },
            {
              "id": "e707c106-36e4-4810-88f0-06d8acf822e8",
              "idHeader": "f7c599bf-bbb4-42ce-919b-663eb547683f",
              "text": "Pâte de tomate",
              "checked": false,
              "subs": []
            }
          ],
          "idCategory": "ffa8eb95-eb5d-488f-bace-208c490fa609"
        },
        {
          "id": "fd09990c-25b1-4e82-a213-d59e4aeec056",
          "name": "Booze",
          "items": [
            {
              "id": "309f38f4-f5ec-4e01-84ed-ad433544264f",
              "idHeader": "fd09990c-25b1-4e82-a213-d59e4aeec056",
              "text": "Gin",
              "checked": false,
              "subs": []
            },
            {
              "id": "7a5902b1-e31d-4384-a497-01c0a021ca10",
              "idHeader": "fd09990c-25b1-4e82-a213-d59e4aeec056",
              "text": "Saké",
              "checked": true,
              "subs": []
            },
            {
              "id": "a0551a8e-f2b5-4d2c-85bb-9f2cc19aa028",
              "idHeader": "fd09990c-25b1-4e82-a213-d59e4aeec056",
              "text": "Vino",
              "checked": false,
              "subs": [
                {
                  "id": "261c0aaf-5e90-4088-bec1-22be9ce0c6e1",
                  "idItem": "a0551a8e-f2b5-4d2c-85bb-9f2cc19aa028",
                  "text": "Bulles",
                  "rank": 2,
                  "checked": false
                },
                {
                  "id": "fe774eee-2f71-4c5f-9f85-d3d75aea304c",
                  "idItem": "a0551a8e-f2b5-4d2c-85bb-9f2cc19aa028",
                  "text": "Blanco",
                  "rank": 1,
                  "checked": false
                }
              ]
            },
            {
              "id": "a39a60e4-ee3f-4ad9-929f-74cb648f14d7",
              "idHeader": "fd09990c-25b1-4e82-a213-d59e4aeec056",
              "text": "Pastis",
              "checked": false,
              "subs": [
                {
                  "id": "b4a51013-5d74-49a1-afc1-f61666df6ca8",
                  "idItem": "a39a60e4-ee3f-4ad9-929f-74cb648f14d7",
                  "text": "berger",
                  "rank": 1,
                  "checked": false
                }
              ]
            }
          ],
          "idCategory": "ffa8eb95-eb5d-488f-bace-208c490fa609"
        }
      ]
    }
  ]
}